odoo8_addon_l10n_ch_payment_slip-8.0.3.0.0-nspkg.pth
odoo_addons/l10n_ch_payment_slip/README.rst
odoo_addons/l10n_ch_payment_slip/__init__.py
odoo_addons/l10n_ch_payment_slip/__openerp__.py
odoo_addons/l10n_ch_payment_slip/account_invoice_view.xml
odoo_addons/l10n_ch_payment_slip/bank.py
odoo_addons/l10n_ch_payment_slip/bank_view.xml
odoo_addons/l10n_ch_payment_slip/company.py
odoo_addons/l10n_ch_payment_slip/company_view.xml
odoo_addons/l10n_ch_payment_slip/invoice.py
odoo_addons/l10n_ch_payment_slip/payment.py
odoo_addons/l10n_ch_payment_slip/payment_slip.py
odoo_addons/l10n_ch_payment_slip/i18n/am.po
odoo_addons/l10n_ch_payment_slip/i18n/ar.po
odoo_addons/l10n_ch_payment_slip/i18n/bg.po
odoo_addons/l10n_ch_payment_slip/i18n/bs.po
odoo_addons/l10n_ch_payment_slip/i18n/ca.po
odoo_addons/l10n_ch_payment_slip/i18n/ca_ES.po
odoo_addons/l10n_ch_payment_slip/i18n/cs.po
odoo_addons/l10n_ch_payment_slip/i18n/da.po
odoo_addons/l10n_ch_payment_slip/i18n/de.po
odoo_addons/l10n_ch_payment_slip/i18n/el_GR.po
odoo_addons/l10n_ch_payment_slip/i18n/en_AU.po
odoo_addons/l10n_ch_payment_slip/i18n/en_GB.po
odoo_addons/l10n_ch_payment_slip/i18n/es.po
odoo_addons/l10n_ch_payment_slip/i18n/es_AR.po
odoo_addons/l10n_ch_payment_slip/i18n/es_CL.po
odoo_addons/l10n_ch_payment_slip/i18n/es_CO.po
odoo_addons/l10n_ch_payment_slip/i18n/es_CR.po
odoo_addons/l10n_ch_payment_slip/i18n/es_DO.po
odoo_addons/l10n_ch_payment_slip/i18n/es_EC.po
odoo_addons/l10n_ch_payment_slip/i18n/es_MX.po
odoo_addons/l10n_ch_payment_slip/i18n/es_PE.po
odoo_addons/l10n_ch_payment_slip/i18n/es_PY.po
odoo_addons/l10n_ch_payment_slip/i18n/es_VE.po
odoo_addons/l10n_ch_payment_slip/i18n/et.po
odoo_addons/l10n_ch_payment_slip/i18n/eu.po
odoo_addons/l10n_ch_payment_slip/i18n/fa.po
odoo_addons/l10n_ch_payment_slip/i18n/fi.po
odoo_addons/l10n_ch_payment_slip/i18n/fr.po
odoo_addons/l10n_ch_payment_slip/i18n/fr_CA.po
odoo_addons/l10n_ch_payment_slip/i18n/fr_CH.po
odoo_addons/l10n_ch_payment_slip/i18n/fr_FR.po
odoo8_addon_l10n_ch_payment_slip-8.0.3.0.0.dist-info/METADATA
odoo8_addon_l10n_ch_payment_slip-8.0.3.0.0.dist-info/WHEEL
odoo8_addon_l10n_ch_payment_slip-8.0.3.0.0.dist-info/namespace_packages.txt
odoo8_addon_l10n_ch_payment_slip-8.0.3.0.0.dist-info/top_level.txt
odoo8_addon_l10n_ch_payment_slip-8.0.3.0.0.dist-info/RECORD
