Metadata-Version: 2.1
Name: odoo8-addon-l10n-ch-payment-slip
Version: 8.0.3.0.0
Summary: Print ESR/BVR payment slip with your invoices
Home-page: http://www.camptocamp.com
Author: Camptocamp,Odoo Community Association (OCA)
Author-email: support@odoo-community.org
License: AGPL-3
Platform: UNKNOWN
Classifier: Programming Language :: Python
Classifier: Framework :: Odoo
Classifier: License :: OSI Approved :: GNU Affero General Public License v3
Requires-Python: ~=2.7
Requires-Dist: odoo8-addon-base-transaction-id
Requires-Dist: odoo8-addon-l10n-ch-base-bank
Requires-Dist: odoo (<9.0a,>=8.0a)
